<?xml version="1.0" encoding="utf-8"?>
<class>
	<student id="01">
		<keresztnev>Tihor</keresztnev>
		<vezeteknev>Fruzsina</vezeteknev>
		<becenev>Fruzsi</becenev>
		<kor>20</kor>
		<osztondij>600000</osztondij>
	</student>
	<student id="02">
		<keresztnev>Kek</keresztnev>
		<vezeteknev>Dora</vezeteknev>
		<becenev>Dorka</becenev>
		<kor>20</kor>
		<osztondij>520000</osztondij>
	</student>
	<student id="03">
		<keresztnev>Zsoldos</keresztnev>
		<vezeteknev>Andrea</vezeteknev>
		<becenev>Andi</becenev>
		<kor>20</kor>
		<osztondij>450000</osztondij>
	</student>
</class>
